spaceremover.py
extraspaceremover-0.0.1.dist-info/LICENCE.txt
extraspaceremover-0.0.1.dist-info/METADATA
extraspaceremover-0.0.1.dist-info/WHEEL
extraspaceremover-0.0.1.dist-info/top_level.txt
extraspaceremover-0.0.1.dist-info/RECORD
