Metadata-Version: 2.1
Name: extraspaceremover
Version: 0.0.1
Summary: Remove extra spaces from a text
Home-page: https://github.com/has-abi
Author: Hassane Abida
Author-email: abidahass.uca@gmail.com
License: UNKNOWN
Platform: UNKNOWN
Classifier: Programming Language :: Python :: 3
Classifier: License :: OSI Approved :: GNU General Public License v2 (GPLv2)
Classifier: Operating System :: OS Independent
License-File: LICENCE.txt
Provides-Extra: dev
Requires-Dist: pytest (>=3.7) ; extra == 'dev'
